strobes_intel_client/__init__.py
strobes_intel_client/__version__.py
strobes_intel_client/input.py
strobes_intel_client/main.py
strobes_intel_client/models.py
Strobes_Intel_Client-0.0.dev1.dist-info/LICENSE
Strobes_Intel_Client-0.0.dev1.dist-info/METADATA
Strobes_Intel_Client-0.0.dev1.dist-info/WHEEL
Strobes_Intel_Client-0.0.dev1.dist-info/entry_points.txt
Strobes_Intel_Client-0.0.dev1.dist-info/top_level.txt
Strobes_Intel_Client-0.0.dev1.dist-info/RECORD
