Metadata-Version: 2.1
Name: Strobes-Intel-Client
Version: 0.0.dev1
Summary: Strobes Intel Client is a service which communicates with strobes intel and fetches cve data in pydantic model.
Home-page: https://github.com/strobes-co/strobes-intel-client
Author: Akhil Reni
Author-email: akhil@wesecureapp.com
License: GPLv3
Platform: UNKNOWN
Requires-Python: >=3.6
Requires-Dist: requests (==2.25.1)
Requires-Dist: pydantic (==1.9.0)
